grafeno/__init__.py
grafeno/graph.py
grafeno/pipeline.py
grafeno/setup.py
grafeno/jupyter/Makefile
grafeno/jupyter/__init__.py
grafeno/jupyter/app.es5
grafeno/jupyter/app.html
grafeno/jupyter/app.js
grafeno/jupyter/package-lock.json
grafeno/jupyter/package.json
grafeno/jupyter/visualize.py
grafeno/linearizers/__init__.py
grafeno/linearizers/all_concepts.py
grafeno/linearizers/analyzer.py
grafeno/linearizers/base.py
grafeno/linearizers/cluster_extract.py
grafeno/linearizers/cypher_base.py
grafeno/linearizers/cypher_create.py
grafeno/linearizers/cypher_query.py
grafeno/linearizers/example_nlg.py
grafeno/linearizers/extract.py
grafeno/linearizers/node_edges.py
grafeno/linearizers/prolog.py
grafeno/linearizers/semtriplets.py
grafeno/linearizers/simplenlg.py
grafeno/linearizers/triplets.py
grafeno/linearizers/simplenlg_lib/Py4JServer.class
grafeno/linearizers/simplenlg_lib/py4j0.6.jar
grafeno/linearizers/simplenlg_lib/simplenlg-3.8.jar
grafeno/operations/__init__.py
grafeno/operations/cluster.py
grafeno/operations/clustering.py
grafeno/operations/filter_edges.py
grafeno/operations/generalize.py
grafeno/operations/graft.py
grafeno/operations/hits.py
grafeno/operations/louvain_cluster.py
grafeno/operations/markov_cluster.py
grafeno/operations/rename_concepts.py
grafeno/operations/spot_domain.py
grafeno/transformers/__init__.py
grafeno/transformers/__utils.py
grafeno/transformers/adjectives.py
grafeno/transformers/adverbs.py
grafeno/transformers/all.py
grafeno/transformers/attr_class.py
grafeno/transformers/base.py
grafeno/transformers/concept_class.py
grafeno/transformers/conjunction.py
grafeno/transformers/copula.py
grafeno/transformers/edge_reverse.py
grafeno/transformers/extend.py
grafeno/transformers/freeling_parse.py
grafeno/transformers/genitive.py
grafeno/transformers/index.py
grafeno/transformers/interrogative.py
grafeno/transformers/keep_deps.py
grafeno/transformers/lenient.py
grafeno/transformers/lesk_link.py
grafeno/transformers/negation.py
grafeno-0.4.0.dist-info/METADATA
grafeno-0.4.0.dist-info/WHEEL
grafeno-0.4.0.dist-info/entry_points.txt
grafeno-0.4.0.dist-info/licenses/LICENSE
grafeno-0.4.0.dist-info/RECORD
