Metadata-Version: 2.1
Name: grafeno
Version: 0.4.0
Summary: Concept graph library
Author-email: "Antonio F. G. Sevilla" <afgs@ucm.es>
License: AGPL-3.0
License-File: LICENSE
Requires-Python: ~=3.7.0
Requires-Dist: networkx~=2.2
Requires-Dist: pip>=24.0
Requires-Dist: pyyaml
Requires-Dist: spacy~=2.0
Provides-Extra: lexical
Requires-Dist: nltk; extra == 'lexical'
Provides-Extra: modules
Requires-Dist: numpy; extra == 'modules'
Requires-Dist: pexpect; extra == 'modules'
Requires-Dist: scipy; extra == 'modules'
Provides-Extra: web
Requires-Dist: bottle; extra == 'web'
